pyreportjasper/__init__.py
pyreportjasper/application_class_path.py
pyreportjasper/config.py
pyreportjasper/db.py
pyreportjasper/pyreportjasper.py
pyreportjasper/report.py
tests/__init__.py
tests/discover.py
tests/test_pyreportjasper.py
tests/test_report.py
pyreportjasperbytesUVV-2.1.4.dist-info/LICENSE
pyreportjasperbytesUVV-2.1.4.dist-info/METADATA
pyreportjasperbytesUVV-2.1.4.dist-info/WHEEL
pyreportjasperbytesUVV-2.1.4.dist-info/top_level.txt
pyreportjasperbytesUVV-2.1.4.dist-info/RECORD
