Metadata-Version: 2.1
Name: pyreportjasperbytesUVV
Version: 2.1.4
Summary: This package aims to be a solution to compile and process JasperReports (.jrxml & .jasper files).
Home-page: https://github.com/EduardoSFReis/pyreportjasper
Download-URL: https://pypi.python.org/pypi/pyreportjasper/2.1.4
Author: Eduardo Soares Franco Reis
Author-email: edufrancoreis@hotmail.com
Maintainer: Eduardo Soares Franco Reis
Maintainer-email: edufrancoreis@hotmail.com
License: GPLv3
Project-URL: Documentation, https://pyreportjasper.readthedocs.io/en/master/
Project-URL: Code, https://github.com/EduardoSFReis/pyreportjasper
Project-URL: Issue tracker, https://github.com/EduardoSFReis/pyreportjasper/issues
Keywords: report jasper python
Classifier: Intended Audience :: Developers
Classifier: Operating System :: OS Independent
Classifier: Topic :: Software Development :: Libraries :: Python Modules
Classifier: License :: OSI Approved :: GNU General Public License v3 (GPLv3)
Classifier: Programming Language :: Python :: 3.8
Classifier: Programming Language :: Python :: 3.9
Classifier: Programming Language :: Python :: 3.10
Classifier: Programming Language :: Python :: 3.11
Requires-Python: >=3.7
License-File: LICENSE
Requires-Dist: jpype1
Provides-Extra: docs
Requires-Dist: readthedocs-sphinx-ext; extra == "docs"
Requires-Dist: sphinx; extra == "docs"
Requires-Dist: sphinx-rtd-theme; extra == "docs"
Requires-Dist: recommonmark; extra == "docs"
Requires-Dist: commonmark; extra == "docs"
Requires-Dist: mock; extra == "docs"
Requires-Dist: docutils; extra == "docs"
Requires-Dist: Pygments; extra == "docs"
